stockmanage_lib/__init__.py
stockmanage_lib/manager.py
stockmanage_simple_lib-0.1.0.dist-info/METADATA
stockmanage_simple_lib-0.1.0.dist-info/WHEEL
stockmanage_simple_lib-0.1.0.dist-info/top_level.txt
stockmanage_simple_lib-0.1.0.dist-info/RECORD
